{
    "formOriginal":  "SIGREDCO",
    "layoutFile":  "C:\\4c\\tasks\\task074\\layout.json",
    "timestamp":  "2026-06-03T22:54:49",
    "prgFile":  "C:\\4c\\projeto\\app\\forms\\relatorios\\Formsigredco.prg",
    "summary":  {
                    "infos":  2,
                    "unmatched":  0,
                    "layoutObjects":  2,
                    "errors":  0,
                    "matched":  2,
                    "prgObjects":  4,
                    "warnings":  0
                },
    "thresholdPx":  5,
    "issues":  [
                   {
                       "message":  "Objeto no .prg sem correspondente no layout.json (pode ser auxiliar: labels, containers de layout)",
                       "line":  267,
                       "path":  "THIS.THIS.cnt_4c_Cabecalho",
                       "property":  null,
                       "object":  "cnt_4c_Cabecalho",
                       "severity":  "INFO",
                       "actual":  null,
                       "page":  "",
                       "class":  "Container",
                       "delta":  null,
                       "expected":  null
                   },
                   {
                       "message":  "Objeto no .prg sem correspondente no layout.json (pode ser auxiliar: labels, containers de layout)",
                       "line":  320,
                       "path":  "THIS.THIS.cmg_4c_Botoes",
                       "property":  null,
                       "object":  "cmg_4c_Botoes",
                       "severity":  "INFO",
                       "actual":  null,
                       "page":  "",
                       "class":  "CommandGroup",
                       "delta":  null,
                       "expected":  null
                   }
               ]
}
