{
    "arquivo":  "C:\\4c\\projeto\\app\\classes\\ProdutoBO.prg",
    "timestamp":  "2026-04-12T02:57:27",
    "correcoes":  [
                      {
                          "Tipo":  "SQL_COLUNA_LEGADA",
                          "Linha":  1073,
                          "Original":  "UsuaAlts (na linha: loc_cSQL = \"SELECT cpros, dpros, cgrus, sgrus, reffs, usuaalts, situas\" + ;)",
                          "Corrigido":  "(WARNING) Usar \u0027usuaalts\u0027 em vez de \u0027UsuaAlts\u0027",
                          "Descricao":  "Coluna \u0027UsuaAlts\u0027 eh nome legado CamelCase - schema real usa \u0027usuaalts\u0027"
                      },
                      {
                          "Tipo":  "NVL_BIT_FIELD_WARN",
                          "Linha":  420,
                          "Original":  "THIS.this_lFlagctabs = (NVL(flagctabs, 0) = 1)",
                          "Corrigido":  "(revisar manualmente)",
                          "Descricao":  "NVL(campo,0)=1 sem assignment detectado. IIF nao eh seguro (avalia ambos ramos). Converter para IF/ELSE/ENDIF manualmente"
                      },
                      {
                          "Tipo":  "NVL_BIT_FIELD_WARN",
                          "Linha":  421,
                          "Original":  "THIS.this_lTcomps    = (NVL(tcomps,    0) = 1)",
                          "Corrigido":  "(revisar manualmente)",
                          "Descricao":  "NVL(campo,0)=1 sem assignment detectado. IIF nao eh seguro (avalia ambos ramos). Converter para IF/ELSE/ENDIF manualmente"
                      },
                      {
                          "Tipo":  "NVL_BIT_FIELD_WARN",
                          "Linha":  422,
                          "Original":  "THIS.this_lTransps   = (NVL(transps,   0) = 1)",
                          "Corrigido":  "(revisar manualmente)",
                          "Descricao":  "NVL(campo,0)=1 sem assignment detectado. IIF nao eh seguro (avalia ambos ramos). Converter para IF/ELSE/ENDIF manualmente"
                      },
                      {
                          "Tipo":  "NVL_BIT_FIELD_WARN",
                          "Linha":  423,
                          "Original":  "THIS.this_lImpetiqs  = (NVL(impetiqs,  0) = 1)",
                          "Corrigido":  "(revisar manualmente)",
                          "Descricao":  "NVL(campo,0)=1 sem assignment detectado. IIF nao eh seguro (avalia ambos ramos). Converter para IF/ELSE/ENDIF manualmente"
                      },
                      {
                          "Tipo":  "NVL_BIT_FIELD_WARN",
                          "Linha":  424,
                          "Original":  "THIS.this_lChkfunds  = (NVL(chkfunds,  0) = 1)",
                          "Corrigido":  "(revisar manualmente)",
                          "Descricao":  "NVL(campo,0)=1 sem assignment detectado. IIF nao eh seguro (avalia ambos ramos). Converter para IF/ELSE/ENDIF manualmente"
                      },
                      {
                          "Tipo":  "NVL_BIT_FIELD_WARN",
                          "Linha":  427,
                          "Original":  "THIS.this_lVarias      = (NVL(varias,      0) = 1)",
                          "Corrigido":  "(revisar manualmente)",
                          "Descricao":  "NVL(campo,0)=1 sem assignment detectado. IIF nao eh seguro (avalia ambos ramos). Converter para IF/ELSE/ENDIF manualmente"
                      },
                      {
                          "Tipo":  "NVL_BIT_FIELD_WARN",
                          "Linha":  428,
                          "Original":  "THIS.this_lConsigs     = (NVL(consigs,     0) = 1)",
                          "Corrigido":  "(revisar manualmente)",
                          "Descricao":  "NVL(campo,0)=1 sem assignment detectado. IIF nao eh seguro (avalia ambos ramos). Converter para IF/ELSE/ENDIF manualmente"
                      },
                      {
                          "Tipo":  "NVL_BIT_FIELD_WARN",
                          "Linha":  429,
                          "Original":  "THIS.this_lFabrproprs  = (NVL(fabrproprs,  0) = 1)",
                          "Corrigido":  "(revisar manualmente)",
                          "Descricao":  "NVL(campo,0)=1 sem assignment detectado. IIF nao eh seguro (avalia ambos ramos). Converter para IF/ELSE/ENDIF manualmente"
                      },
                      {
                          "Tipo":  "NVL_BIT_FIELD_WARN",
                          "Linha":  430,
                          "Original":  "THIS.this_lEncoms      = (NVL(encoms,      0) = 1)",
                          "Corrigido":  "(revisar manualmente)",
                          "Descricao":  "NVL(campo,0)=1 sem assignment detectado. IIF nao eh seguro (avalia ambos ramos). Converter para IF/ELSE/ENDIF manualmente"
                      },
                      {
                          "Tipo":  "NVL_BIT_FIELD_WARN",
                          "Linha":  431,
                          "Original":  "THIS.this_lChkgarvit   = (NVL(chkgarvit,   0) = 1)",
                          "Corrigido":  "(revisar manualmente)",
                          "Descricao":  "NVL(campo,0)=1 sem assignment detectado. IIF nao eh seguro (avalia ambos ramos). Converter para IF/ELSE/ENDIF manualmente"
                      },
                      {
                          "Tipo":  "NVL_BIT_FIELD_WARN",
                          "Linha":  432,
                          "Original":  "THIS.this_lCravcers    = (NVL(cravcers,    0) = 1)",
                          "Corrigido":  "(revisar manualmente)",
                          "Descricao":  "NVL(campo,0)=1 sem assignment detectado. IIF nao eh seguro (avalia ambos ramos). Converter para IF/ELSE/ENDIF manualmente"
                      },
                      {
                          "Tipo":  "NVL_BIT_FIELD_WARN",
                          "Linha":  433,
                          "Original":  "THIS.this_lProdwebs    = (NVL(prodwebs,    0) = 1)",
                          "Corrigido":  "(revisar manualmente)",
                          "Descricao":  "NVL(campo,0)=1 sem assignment detectado. IIF nao eh seguro (avalia ambos ramos). Converter para IF/ELSE/ENDIF manualmente"
                      }
                  ],
    "totalCorrecoes":  13
}
